{
  "name": "Jim Chandler",
  "age": 57,
  "address": {
    "street": "Lofdas Turnpike",
    "city": "Temovuk",
    "state": "ID",
    "zip": "70253"
  },
  "contact": {
    "phone": "(634) 223-4108",
    "servicePhone": "800173918"
  },
  "birthday": "1968-03-28T04:00:50.633Z",
  "ip": "110.133.14.159",
  "foo": "bar",
  "profile": {
    "about": "Fawkiw pesgeid tuj alisarob mubakhot zinro josoju ki gigsu wac tozcafika jigwetwid wibemo pa dag go hoomjov pef. Zuzwir ju lalu aviririr taturbon hucnir ivohojol hurdetcon fapacus efo raawe dow belzigu zedup vu ca moncip amuti. Geuzagu te uvelek me bud seh ibazad mihe kaz cuw ibbocul gozev. Bike fi nikobno low sokne ar sigiro logamhib eg ezibipa bawi doep kebob. Amazo uvzancu nodtikce volkozho lisoriz kihesup rocugive ke hatdak ag otoj wewetobu kehdu oma.",
    "bio": "Fes mehe gob wuz larfo nuedgu tobul bef lafu ved undov mapol noake movfap zagged kofoh. Caljefju ultik rowge siafmu om izi focvo gij rauvidag ziumugoz ze zenuj moin fece zibeho upermef. De berwava jionebi se vubeovo tur gagak jedbehbi upa sapahlo avoefgut duno bimatasah fajafnok oz ehrihme. Fecibpe sa wifev celdin okuzeh wo naem moctawu isoif tiv wesco ducisata horhetpo lulupni ifuzec kumuvhi fur."
  },
  "apiKey": "2028367f4551d477bb3b41d04b7f15fbc73b4cc17db12634db388a079aae8a1c",
  "currency": {
    "code": "SVC",
    "name": "El Salvador Colon"
  }
}