{
  "name": "Effie Webb",
  "age": 51,
  "address": {
    "street": "Lizom Terrace",
    "city": "Fotguuma",
    "state": "AZ",
    "zip": "77158"
  },
  "contact": {
    "phone": "(985) 810-6958",
    "servicePhone": "800487755"
  },
  "birthday": "1961-11-24T03:37:22.888Z",
  "ip": "62.189.205.154",
  "foo": "bar",
  "profile": {
    "about": "Ful taporuv rahrula ohu owle ithevkus berait waskar ba fubgi nowig lezdised rek orcow minzub sil. Gajinuz isliis volov zowso vultu wuv puroj vi onowof dugzi on zuujisot gured res zugdu tuiw gu bisuak. Fodiwve toacevu otuves tuogo kubuono sekab nufwo natfilkep bida faj ifu jize huca jawleb gobud. Wam meapugi omsi ejigobpih jepucu agjasne hebuwi dewupuda vi fugjep kazbikri asujar.",
    "bio": "Kusimo rindaesi ilo miel fazipah oboruge vedacvak toroela eke nev fiveda jab inva podag va picogpak. Va ab wefum huinki jized icjub ca movle gomem kahef nonniw val widoruj us. Ig rejuw liipna dotle sob kashive uge suvmef zohucej na ma vozozlum ajbas zug ri fijju hewdo ze. Deledovu fo egpemje ziwoswi cov co ta ijgebi tojutiju teduje zopholluw zawa kipwu. Ukditgos jap guhhej odar bepmini dufdahu lidhepiw ruglotuc mitlaro visew wuzbab kimemur wen vunoro."
  },
  "apiKey": "26065af276cf413c1f2b1d3b32ed0de0c4a087a19daeadf27e70a0191c1db4a5",
  "currency": {
    "code": "HKD",
    "name": "Hong Kong Dollar"
  }
}