{
  "name": "Vincent Greer",
  "age": 37,
  "address": {
    "street": "Hobiba Highway",
    "city": "Nehkowi",
    "state": "OK",
    "zip": "81158"
  },
  "contact": {
    "phone": "(725) 787-2289",
    "servicePhone": "800783867"
  },
  "birthday": "2006-07-23T03:08:14.066Z",
  "ip": "2.175.104.81",
  "foo": "bar",
  "profile": {
    "about": "Nub keopwel de ad genemgez pajaf eszoku si wizu zofgalwa gosfap tehhijep elordel keajnac. Ta ho cuawge sidew rojomvi mi akeuz aci ubopivzuv fo ega piw to giru nubawagu cit neoz wovu. Ejon ca egi dafkez amo muse inajo ciofesub jegoj wa hil uh cabo tilo cariwmu hodewav fututna. Totuigu fula gigahkok ug fohjah darow lagu ifiohom impaone deztulor dapal pigob batzo azuvi na riucuji urekaucu. Bad rilwanec ozolo ika igu ozorebjo kuv votso le kaujli igmuada efonibel pa tetco zajfu torucva joftos.",
    "bio": "Jeum kiraat tidew ekate zazad lak akoabu ramecfil vukzej cujumaf ocpi rogafogu goc webejho. Uvuzosus ete sijoplup ozvukfu zeghik itazo nu ciwiv musul vewi jefosra to doj zum. Rebaj limmaw ah ef zirbofpu ibjorer ti jeec pevef jaet ciz asok atopu mug."
  },
  "apiKey": "27d25b252295867c360540ba6e1d2bc77e4efa8d972644260179298d8fb08f7a",
  "currency": {
    "code": "NZD",
    "name": "New Zealand Dollar"
  }
}