{
  "name": "Elmer Lamb",
  "age": 41,
  "address": {
    "street": "Fubro Loop",
    "city": "Jodevu",
    "state": "WA",
    "zip": "16305"
  },
  "contact": {
    "phone": "(319) 343-8381",
    "servicePhone": "800823832"
  },
  "birthday": "1995-12-24T19:47:29.738Z",
  "ip": "132.243.80.57",
  "foo": "bar",
  "profile": {
    "about": "Nurkuz humhagog luvawena muz wan feh measto uw miz livmo sewluhub wonamig ob to. Peikuic sope ge veedeta koto bik ip iw an seorhub kujahza ihabew hi. Jitelal kik canhotad dodfimep vumvuw vakerot wumaso emomijog if ep hoceho bovte rulig babav obaultab reucu sawav. Zopvo agoapooh kisiro bu jiv ibca ko bumukuta otiewa ginlut apce lutegna za uhgun wor.",
    "bio": "Fum sa rualki satkizge lu noir vugeri ewudakug ovozun ofeaduejo giwublo fioresuv. Lirjomlin ijara ku wedohso zul rihodo hawagza riopre fo oluwe hemocad nuliztu pimarwem poluhfa lo davohe otsedof kicuw. Gug otud eb aleolo lamiez no wi ijitavat disavsa wu sakow ifa gu kibe jicil fugtu bilsicol henithes. Ricloere penku de cow nafa je opupijti bitida bavawak muw ijurow uc laovo dujfojopi. Bicup webujke ba adociew rune bawsagwa himduf eti voldel donoc oseliz buokoko nirfa goglosuk had. Cubded vub dafpamoh ji kokpatluv jo lamdo denad zehcaj nojro okidile cechu anzapuf tusulmes jageko nedake jevsare. Ridorum kardugig wavfev woteope giwatzus lictawlak ag hulel od osev cukusiv gizaru uwle vadgile pazabec zuptadipu gasrin."
  },
  "apiKey": "7401ef630daba283c76ab15b8750c06cc98df460b557d18b20ea2b0776c29c68",
  "currency": {
    "code": "ETB",
    "name": "Ethiopia Birr"
  }
}